{
    "Version": "2012-10-17",
    "Statement": [
        {
            "Sid": "AllowCloudFrontServicePrincipal",
            "Effect": "Allow",
            "Principal": { "Service": "cloudfront.amazonaws.com" },
            "Action": "s3:GetObject",
            "Resource": "${bucket_arn}/*",
            "Condition": {
                "StringEquals": { "AWS:SourceArn": "${cloudfront_arn}" }
            }
        },
        {
            "Sid": "AllowGitHubActions",
            "Effect": "Allow",
            "Principal": {
            "AWS": "${github_actions_role_arn}"
            },
            "Action": [
                "s3:PutObject",
                "s3:ListBucket",
                "s3:DeleteObject",
                "s3:GetObject"
            ],
            "Resource": [
                "${bucket_arn}",
                "${bucket_arn}/*"
            ]
        }
    ]
}